{
	"name": "derived colun",
	"properties": {
		"type": "MappingDataFlow",
		"typeProperties": {
			"sources": [
				{
					"dataset": {
						"referenceName": "employeedata",
						"type": "DatasetReference"
					},
					"name": "emp"
				}
			],
			"sinks": [
				{
					"dataset": {
						"referenceName": "outputdataflow",
						"type": "DatasetReference"
					},
					"name": "sink1"
				}
			],
			"transformations": [
				{
					"name": "DerivedColumn1"
				}
			],
			"script": "source(output(\n\t\tempid as string,\n\t\tname as string,\n\t\tcountry as string,\n\t\tdepartment as string\n\t),\n\tallowSchemaDrift: true,\n\tvalidateSchema: false,\n\tignoreNoFilesFound: false) ~> emp\nemp derive(country = iif(isNull(country),'unknown',upper(country))) ~> DerivedColumn1\nDerivedColumn1 sink(allowSchemaDrift: true,\n\tvalidateSchema: false,\n\tpartitionFileNames:['derivedcoloutput6'],\n\tmapColumn(\n\t\tempid,\n\t\tname,\n\t\tcountry,\n\t\tdepartment\n\t),\n\tpartitionBy('hash', 1),\n\tskipDuplicateMapInputs: true,\n\tskipDuplicateMapOutputs: true) ~> sink1"
		}
	}
}